ezdag/__init__.py
ezdag/_version.py
ezdag/dags.py
ezdag/format.py
ezdag/layers.py
ezdag/options.py
ezdag/path.py
ezdag/py.typed
ezdag/tests/__init__.py
ezdag/tests/test_dags.py
ezdag/tests/test_options.py
ezdag/tests/data/combine_bins.sub
ezdag/tests/data/my_dag.dag
ezdag/tests/data/my_dag.sh
ezdag/tests/data/process_bins.sub
ezdag/tests/data/abs/no_transfer/aggregate_by_key.sub
ezdag/tests/data/abs/no_transfer/count_dag.dag
ezdag/tests/data/abs/no_transfer/count_dag.sh
ezdag/tests/data/abs/no_transfer/count_keys.sub
ezdag/tests/data/abs/no_transfer/partition_by_key.sub
ezdag/tests/data/abs/transfer/aggregate_by_key.sub
ezdag/tests/data/abs/transfer/count_dag.dag
ezdag/tests/data/abs/transfer/count_dag.sh
ezdag/tests/data/abs/transfer/count_keys.sub
ezdag/tests/data/abs/transfer/partition_by_key.sub
ezdag/tests/data/rel/no_transfer/aggregate_by_key.sub
ezdag/tests/data/rel/no_transfer/count_dag.dag
ezdag/tests/data/rel/no_transfer/count_dag.sh
ezdag/tests/data/rel/no_transfer/count_keys.sub
ezdag/tests/data/rel/no_transfer/partition_by_key.sub
ezdag/tests/data/rel/transfer/aggregate_by_key.sub
ezdag/tests/data/rel/transfer/count_dag.dag
ezdag/tests/data/rel/transfer/count_dag.sh
ezdag/tests/data/rel/transfer/count_keys.sub
ezdag/tests/data/rel/transfer/partition_by_key.sub
ezdag/tests/data/url/transfer/aggregate_by_key.sub
ezdag/tests/data/url/transfer/count_dag.dag
ezdag/tests/data/url/transfer/count_dag.sh
ezdag/tests/data/url/transfer/count_keys.sub
ezdag/tests/data/url/transfer/partition_by_key.sub
ezdag-0.4.0.dist-info/METADATA
ezdag-0.4.0.dist-info/WHEEL
ezdag-0.4.0.dist-info/licenses/AUTHORS.md
ezdag-0.4.0.dist-info/licenses/LICENSE
ezdag-0.4.0.dist-info/RECORD
